secrethub/__init__.py
secrethub/_secrethub.cp39-win_amd64.pyd
secrethub/secrethub.py
secrethub-0.1.1.dist-info/LICENSE
secrethub-0.1.1.dist-info/METADATA
secrethub-0.1.1.dist-info/WHEEL
secrethub-0.1.1.dist-info/top_level.txt
secrethub-0.1.1.dist-info/RECORD
