Metadata-Version: 2.1
Name: secrethub
Version: 0.1.1
Summary: Python client for the SecretHub Secrets Management API
Home-page: https://secrethub.io/
Author: SecretHub
Author-email: support@secrethub.io
License: Apache License Version 2.0
Project-URL: Source, https://github.com/secrethub/secrethub-python/
Project-URL: Bug Reports, https://github.com/secrethub/secrethub-python/issues
Keywords: secrets management api devops
Platform: UNKNOWN
Classifier: Development Status :: 4 - Beta
Classifier: Intended Audience :: Developers
Classifier: Operating System :: OS Independent
Classifier: Programming Language :: Python
Classifier: Programming Language :: Python :: 3.5
Classifier: Programming Language :: Python :: 3.6
Classifier: Programming Language :: Python :: 3.7
Classifier: Programming Language :: Python :: 3.8
Classifier: Programming Language :: Python :: 3.9
Classifier: Programming Language :: Python :: Implementation :: PyPy
Classifier: Topic :: Software Development :: Libraries :: Python Modules
